Workbook

Sheet Executive Summary
A1: AI Compliance Market & Business Case Analysis
A3: Executive Summary
B5: 1. Project Overview | G5: 2. Business Question | L5: 3. Key Findings — Base Case
B6: Project Title | C6: AI Compliance Market & Business Case Analysis | G6: What is the potential commercial opportunity for an AI-enabled compliance platform targeting Indian technology and SaaS businesses? | L6: Metric | N6: Base Case
B7: Objective | C7: Evaluate the commercial opportunity for an AI-enabled compliance platform targeting Indian technology and SaaS businesses. | L7: TAM | N7: ='Market Sizing'!E5 -> 595.56
L8: SAM | N8: ='Market Sizing'!E8 -> 238.23
B9: Scope | C9: Market sizing, competitive benchmarking, financial modeling and scenario analysis. | L9: SOM Customers | N9: ='Market Sizing'!E10 -> 397
B10: Data | C10: Publicly available information and illustrative business-case assumptions. | L10: SOM Revenue | N10: ='Market Sizing'!E11 -> 11.91
L11: Operating Profit | N11: ='Financial Model'!D15 -> 2.382
L12: Operating Margin | N12: ='Financial Model'!D16 -> 0.2
B14: 4. Market Opportunity | G14: 5.Scenario Analysis | L14: 6. Financial Model
B15: TAM | C15: ='Market Sizing'!E5 -> 595.56 | G15: Scenario | H15: Operating Profit | I15: Operating Margin | L15: Metric | N15: Value
G16: Conservative | H16: =Scenarios!B16 -> 0.12 | I16: =Scenarios!B17 -> 0.03 | L16: Revenue | N16: ='Market Sizing'!E11 -> 11.91
B17: SAM | C17: ='Market Sizing'!E8 -> 238.23 | G17: Base Case | H17: =Scenarios!C16 -> 2.382 | I17: =Scenarios!C17 -> 0.2 | L17: COGS | N17: ='Financial Model'!D6 -> 2.9775
G18: Upside | H18: =Scenarios!D16 -> 8.88 | I18: =Scenarios!D17 -> 0.37 | L18: Gross Profit | N18: ='Financial Model'!D7 -> 8.9325
B19: SOM | C19: ='Market Sizing'!E11 -> 11.91 | G19: Key Insight | H19: Profitability varies materially with customer acquisition, pricing and cost assumptions. | L19: Sales & Marketing | N19: ='Financial Model'!D10 -> 2.9775
L20: R&D | N20: ='Financial Model'!D12 -> 2.382
L21: G&A | N21: ='Financial Model'!D14 -> 1.191
L22: Operating Profit | N22: ='Financial Model'!D15 -> 2.382
L23: Operating Margin | N23: ='Financial Model'!D16 -> 0.2
B25: 7. Competitive Landscape (Summary) | G25: 8. Key Business Considerations | L25: 9. Conclusion
B26: Company | C26: Key Positioning / Capabilities | G26: 1.Validate willingness to pay | I26: ₹3 lakh annual revenue/customer is a model assumption and should be validated against customer willingness to pay and comparable pricing. | L26: The analysis indicates a sizeable potential market for compliance automation among Indian SaaS and technology businesses. Under the base-case assumptions, the model estimates approximately ₹11.9 Cr in annual revenue and ₹2.4 Cr in operating profit. However, the economics vary significantly across scenarios and are sensitive to customer acquisition, willingness to pay and cost assumptions. Competitive benchmarking also indicates that established platforms already offer substantial automation and AI-enabled capabilities.
B27: Sprinto | C27: Compliance automation, 25+ frameworks, 300+ integrations, AI-enabled capabilities | G27: 2. Validate serviceability | I27: 40% of the identified SaaS universe is assumed to be serviceable; the actual addressable segment may be narrower.
B28: Scrut | C28: Compliance and risk automation, 70+ frameworks, 150+ integrations | G28: 3. Validate customer acquisition | I28: 5% obtainable market share is an assumption and requires evidence on achievable customer acquisition.
B29: Vanta | C29: Compliance automation, 300+ integrations, AI-enabled workflows | G29: 4. Differentiate beyond AI | I29: Established competitors already offer AI-enabled compliance capabilities, so AI alone may not provide sufficient differentiation.
B30: Drata | C30: Continuous compliance, AI-enabled GRC, 300+ integrations | G30: 5. Validate scalable economics | I30: Customer acquisition, revenue/customer and operating costs have a material impact on profitability.
B32: Important Note
B33: This is an independent portfolio analysis based on publicly available information and illustrative assumptions. It does not represent the actual financial performance, strategy or recommendations of any company referenced.

Sheet Market Sizing
A1: Source | B1: Input | C1: Assumption | D1: Calculation | E1: Result | F1: Notes
A2: SaaS Browser | B2: No. of Indian SaaS businesses | C2: — | D2: — | E2: =19852 -> 19852 | F2: Directional estimate
A3: Model assumption | B3: Annual revenue/customer | C3: 300000 | D3: — | E3: =C3 -> 300000 | F3: Assumption, not Sprinto's published price
A4: Model | B4: TAM customers | C4: — | D4: Starting SaaS population | E4: =E2 -> 19852 | F4: Total identified population
A5: Model | B5: TAM revenue | C5: — | D5: TAM customers × Annual revenue/customer | E5: =(E4*E3)/10000000 -> 595.56 | F5: Theoretical opportunity
A6: Model assumption | B6: Serviceable % | C6: 0.4 | D6: — | E6: =C6 -> 0.4 | F6: Assumption to be tested
A7: Model | B7: SAM customers | C7: — | D7: TAM customers × Serviceable % | E7: =ROUND(E4*C6,0) -> 7941 | F7: Calculated
A8: Model | B8: SAM revenue | C8: — | D8: SAM customers × Annual revenue/customer | E8: =(E7*E3)/10000000 -> 238.23 | F8: Calculated
A9: Model assumption | B9: Obtainable % | C9: 0.05 | D9: — | E9: =C9 -> 0.05 | F9: Assumption to be tested
A10: Model | B10: SOM customers | C10: — | D10: SAM customers × Obtainable % | E10: =ROUND(E7*E9,0) -> 397 | F10: Calculated
A11: Model | B11: SOM revenue | C11: — | D11: SOM customers × Annual revenue/customer | E11: =(E10*E3)/10000000 -> 11.91 | F11: Calculated

Sheet Benchmarking
A1: Company | B1: Target / Positioning | C1: Framework Coverage | D1: Integrations | E1: Automation | F1: AI Capabilities | G1: Pricing Transparency
A2: Sprinto | B2: Scaling companies / startups | C2: 25+ automated; 200+ digitized | D2: 300+ | E2: High | F2: Strong | G2: Quote-based
A3: Scrut | B3: Compliance / risk teams | C3: 70+ | D3: 150+ | E3: High | F3: Strong | G3: Check
A4: Vanta | B4: Growing businesses | C4: Multiple | D4: 300+ | E4: High | F4: Strong | G4: Check
A5: Drata | B5: Growing / enterprise teams | C5: 25+ | D5: 300+ | E5: High | F5: Strong | G5: Quote-based

Sheet Financial Model
A1: Input | B1: Assumption | C1: Calculation | D1: Result
A2: SOM Customers | B2: — | C2: From Market Sizing | D2: ='Market Sizing'!E10 -> 397
A3: Annual Revenue / Customer | B3: 300000 | C3: — | D3: =B3 -> 300000
A4: Annual Revenue | B4: — | C4: Customers × Revenue/customer | D4: =(D2*D3)/10000000 -> 11.91
A5: COGS % | B5: 0.25 | C5: — | D5: =B5 -> 0.25
A6: COGS | B6: — | C6: Revenue × COGS % | D6: =D4*D5 -> 2.9775
A7: Gross Profit | B7: — | C7: Revenue − COGS | D7: =D4-D6 -> 8.9325
A8: Gross Margin | B8: — | C8: Gross Profit ÷ Revenue | D8: =D7/D4 -> 0.75
A9: Sales & Marketing % | B9: 0.25 | C9: — | D9: =B9 -> 0.25
A10: Sales & Marketing | B10: — | C10: Revenue × S&M % | D10: =D4*D9 -> 2.9775
A11: R&D % | B11: 0.2 | C11: — | D11: =B11 -> 0.2
A12: R&D | B12: — | C12: Revenue × R&D % | D12: =D4*D11 -> 2.382
A13: G&A % | B13: 0.1 | C13: — | D13: =B13 -> 0.1
A14: G&A | B14: — | C14: Revenue × G&A % | D14: =D4*D13 -> 1.191
A15: Operating Profit | B15: — | C15: Gross Profit − S&M − R&D − G&A | D15: =D7-D10-D12-D14 -> 2.382
A16: Operating Margin | B16: — | C16: Operating Profit ÷ Revenue | D16: =D15/D4 -> 0.2

Sheet Scenarios
A1: Input | B1: Conservative | C1: Base Case | D1: Upside
A2: SOM Customers | B2: 200 | C2: 397 | D2: 600
A3: Annual Revenue / Customer | B3: 200000 | C3: 300000 | D3: 400000
A4: COGS % | B4: 0.3 | C4: 0.25 | D4: 0.2
A5: Sales & Marketing % | B5: 0.3 | C5: 0.25 | D5: 0.2
A6: R&D % | B6: 0.25 | C6: 0.2 | D6: 0.15
A7: G&A % | B7: 0.12 | C7: 0.1 | D7: 0.08
A9: Annual Revenue | B9: =B2*B3/10000000 -> 4 | C9: =C2*C3/10000000 -> 11.91 | D9: =D2*D3/10000000 -> 24
A10: COGS | B10: =B9*B4 -> 1.2 | C10: =C9*C4 -> 2.9775 | D10: =D9*D4 -> 4.8
A11: Gross Profit | B11: =B9-B10 -> 2.8 | C11: =C9-C10 -> 8.9325 | D11: =D9-D10 -> 19.2
A12: Gross Margin | B12: =B11/B9 -> 0.7 | C12: =C11/C9 -> 0.75 | D12: =D11/D9 -> 0.8
A13: Sales & Marketing | B13: =B9*B5 -> 1.2 | C13: =C9*C5 -> 2.9775 | D13: =D9*D5 -> 4.8
A14: R&D | B14: =B9*B6 -> 1 | C14: =C9*C6 -> 2.382 | D14: =D9*D6 -> 3.6
A15: G&A | B15: =B9*B7 -> 0.48 | C15: =C9*C7 -> 1.191 | D15: =D9*D7 -> 1.92
A16: Operating Profit | B16: =B11-B13-B14-B15 -> 0.12 | C16: =C11-C13-C14-C15 -> 2.382 | D16: =D11-D13-D14-D15 -> 8.88
A17: Operating Margin | B17: =B16/B9 -> 0.03 | C17: =C16/C9 -> 0.2 | D17: =D16/D9 -> 0.37

Sheet Assumptions & Sources
A1: Item | B1: Value / Assumption | C1: Type | D1: Source / Rationale | E1: URL
A2: Indian SaaS business universe | B2: 19852 | C2: External data | D2: SaaS Browser: | E2: https://saasbrowser.com/en/list-of-saas-in-IN
A3: Annual revenue/customer | B3: 300000 | C3: Assumption | D3: Used for business-case modeling; not published company pricing | E3: —
A4: Serviceable market | B4: 0.4 | C4: Assumption | D4: Model assumption; requires validation | E4: —
A5: Obtainable market | B5: 0.05 | C5: Assumption | D5: Model assumption; requires validation | E5: —
A6: COGS | B6: 0.25 | C6: Assumption | D6: Illustrative financial-model assumption | E6: —
A7: Sales & Marketing | B7: 0.25 | C7: Assumption | D7: Illustrative financial-model assumption | E7: —
A8: R&D | B8: 0.2 | C8: Assumption | D8: Illustrative financial-model assumption | E8: —
A9: G&A | B9: 0.1 | C9: Assumption | D9: Illustrative financial-model assumption | E9: —
A10: Sprinto | B10: — | C10: Competitor source | D10: Sprinto public product/pricing pages | E10: https://sprinto.com/pricing/
A11: Scrut | B11: — | C11: Competitor source | D11: Scrut public website | E11: https://www.scrut.io/
A12: Vanta | B12: — | C12: Competitor source | D12: Vanta public website | E12: https://www.vanta.com/features
A13: Drata | B13: — | C13: Competitor source | D13: Drata public website | E13: https://drata.com/products/compliance-automation
